{
    "တယ်": [],
    "ပါ": [
        "တယ် အစ် မ"
    ],
    "ဘူး": [
        "ဖြစ် နေ တယ်"
    ],
    "လား": [
        "မ သိ ဘူး"
    ],
    "လဲ": [
        "မ သိ ဘူး"
    ],
    "မယ်": [],
    "တာ": [
        "မ ဟုတ် ဘူး",
        "မ ဟုတ် ပါ",
        "အ ကောင်း ဆုံး",
        "ဝန် ယူ မှု"
    ],
    "နော်": [],
    "ပြီ": [],
    "လေ": [],
    "နဲ့": [
        "ပတ် သက် ပြီး"
    ],
    "ပေါ့": [],
    "ရှင့်": [],
    "လို့": [
        "ရ ပါ ပြီ",
        "ရ မ လား",
        "မ ရ ဘူး",
        "ရ ပါ တယ်",
        "အ ဆင် ပြေ",
        "မ ရ ပါ",
        "ရ လား ရှင့်",
        "ရ ပါ သ"
    ],
    "ဗျ": [],
    "တဲ့": [
        "သူ တွေ အ",
        "အ စား အ",
        "သူ တွေ က",
        "သူ တွေ ကို",
        "အ ရာ တွေ",
        "အ ကြောင်း အ",
        "အ ချိန် မှာ",
        "နေ ရာ မှာ"
    ],
    "ဗျာ": []
}